streamlit_auth/__init__.py
streamlit_auth/google_auth.py
streamlit_auth/keycloak_auth.py
streamlit_auth-0.1.7.1.dist-info/LICENSE
streamlit_auth-0.1.7.1.dist-info/METADATA
streamlit_auth-0.1.7.1.dist-info/WHEEL
streamlit_auth-0.1.7.1.dist-info/top_level.txt
streamlit_auth-0.1.7.1.dist-info/RECORD
