Metadata-Version: 2.1
Name: streamlit-auth
Version: 0.1.7.1
Summary: A Python package for creating oauth protected Streamlit apps
Author-email: Hugo Zhu <hugozhu@gmail.com>
License: MIT
Requires-Python: >=3.8.0
License-File: LICENSE
Requires-Dist: streamlit-keycloak
Requires-Dist: httpx-oauth
Requires-Dist: extra_streamlit_components
Requires-Dist: pyjwt
